{"data":{"id":130,"name":"The Losing Edge","season":9,"episode":5,"air_date":"2005-04-06","created_at":"2021-07-14T19:50:54.000000Z","updated_at":"2021-07-14T19:50:54.000000Z","characters":["https://spapi.dev/api/characters/27","https://spapi.dev/api/characters/3","https://spapi.dev/api/characters/10","https://spapi.dev/api/characters/37","https://spapi.dev/api/characters/25","https://spapi.dev/api/characters/152","https://spapi.dev/api/characters/76","https://spapi.dev/api/characters/173","https://spapi.dev/api/characters/187","https://spapi.dev/api/characters/8","https://spapi.dev/api/characters/59","https://spapi.dev/api/characters/56","https://spapi.dev/api/characters/1","https://spapi.dev/api/characters/181","https://spapi.dev/api/characters/74","https://spapi.dev/api/characters/2","https://spapi.dev/api/characters/150","https://spapi.dev/api/characters/26","https://spapi.dev/api/characters/75","https://spapi.dev/api/characters/36","https://spapi.dev/api/characters/137","https://spapi.dev/api/characters/31","https://spapi.dev/api/characters/149","https://spapi.dev/api/characters/179","https://spapi.dev/api/characters/172","https://spapi.dev/api/characters/9","https://spapi.dev/api/characters/55","https://spapi.dev/api/characters/151","https://spapi.dev/api/characters/107","https://spapi.dev/api/characters/182","https://spapi.dev/api/characters/20","https://spapi.dev/api/characters/185","https://spapi.dev/api/characters/186","https://spapi.dev/api/characters/54","https://spapi.dev/api/characters/35","https://spapi.dev/api/characters/171","https://spapi.dev/api/characters/183"],"locations":["https://spapi.dev/api/locations/528","https://spapi.dev/api/locations/68","https://spapi.dev/api/locations/532","https://spapi.dev/api/locations/533","https://spapi.dev/api/locations/487","https://spapi.dev/api/locations/386"]}}